{
  "users": [
    {
      "username": "ars@gamil.com",
      "email": "zrs",
      "password": "1342",
      "id": 1
    },
    {
      "username": "ars@gmail.com",
      "email": "ard",
      "password": "12",
      "id": 2
    }
  ],
  "videos": [
    {
      "videoId": "1",
      "title": "illuminati",
      "imageUrl": "https://i.ytimg.com/vi/tOM-nWPcR4U/maxresdefault.jpg",
      "videoUrl": "https://www.youtube.com/embed/tOM-nWPcR4U?si=_J2A_eQl6nh7ZVzI&autoplay=1",
      "id": 1
    },
    {
      "videoId": "2",
      "title": "vaazha",
      "imageUrl": "https://i.ytimg.com/vi/e1BHIY9p2WU/hqdefault.jpg?sqp=-oaymwEcCNACELwBSFXyq4qpAw4IARUAAIhCGAFwAcABBg==&rs=AOn4CLB6fL4wZfJG2ixFseoavNq-47PfQg",
      "videoUrl": "https://www.youtube.com/embed/e1BHIY9p2WU?si=_J2A_eQl6nh7ZVzI&autoplay=1",
      "id": 2
    },
    {
      "videoId": "2",
      "title": "manavalan thug",
      "imageUrl": "https://i.ytimg.com/vi/_eWvDaztcjI/hq720.jpg?sqp=-oaymwEhCK4FEIIDSFryq4qpAxMIARUAAAAAGAElAADIQj0AgKJD&rs=AOn4CLDY-pWYnrPybaPfi75GaZb00FXt6g",
      "videoUrl": "https://www.youtube.com/embed/_eWvDaztcjI?si=_J2A_eQl6nh7ZVzI&autoplay=1",
      "id": 3
    },
    {
      "videoId": "4",
      "title": "sulaika manzil",
      "imageUrl": "https://i.ytimg.com/vi/C7rJZjB6u7w/maxresdefault.jpg",
      "videoUrl": "https://www.youtube.com/embed/C7rJZjB6u7w?si=_J2A_eQl6nh7ZVzI&autoplay=1",
      "id": 4
    },
    {
      "videoId": "5",
      "title": "king of kotha",
      "imageUrl": "https://i.ytimg.com/vi/X-MZXIXPwFw/maxresdefault.jpg",
      "videoUrl": "https://www.youtube.com/embed/X-MZXIXPwFw?si=_J2A_eQl6nh7ZVzI&autoplay=1",
      "id": 5
    },
    {
      "videoId": "6",
      "title": "kutanthram",
      "imageUrl": "https://i.ytimg.com/vi/9AizchSQURA/maxresdefault.jpg",
      "videoUrl": "https://www.youtube.com/embed/9AizchSQURA?si=_J2A_eQl6nh7ZVzI&autoplay=1",
      "id": 6
    }
  ],
  "catagories": [
    {
      "categoryId": "1",
      "title": "music",
      "videos": [],
      "id": 1
    },
    {
      "categoryId": "2",
      "title": "trailer",
      "videos": [],
      "id": 2
    },
    {
      "categoryId": "2",
      "title": "trailer",
      "videos": [],
      "id": 3
    },
    {
      "categoryId": "2",
      "title": "trailer",
      "videos": [],
      "id": 4
    },
    {
      "categoryId": "1",
      "title": "dd",
      "videos": [],
      "id": 5
    },
    {
      "categoryId": "1",
      "title": "song",
      "videos": [],
      "id": 6
    },
    {
      "categoryId": "1",
      "title": "song",
      "videos": [],
      "id": 7
    },
    {
      "categoryId": "1",
      "title": "music",
      "videos": [],
      "id": 8
    },
    {
      "categoryId": "3",
      "title": "dd",
      "videos": [],
      "id": 9
    },
    {
      "categoryId": "3",
      "title": "dd",
      "videos": [],
      "id": 10
    },
    {
      "categoryId": "3",
      "title": "dd",
      "videos": [],
      "id": 11
    },
    {
      "categoryId": "3",
      "title": "dd",
      "videos": [],
      "id": 12
    }
  ],
  "history": []
}